jplephem/__init__.py
jplephem/__main__.py
jplephem/ascii.py
jplephem/commandline.py
jplephem/daf.py
jplephem/descriptorlib.py
jplephem/ephem.py
jplephem/exceptions.py
jplephem/excerpter.py
jplephem/jpltest.py
jplephem/names.py
jplephem/pck.py
jplephem/spk.py
jplephem/test.py
jplephem-2.21.dist-info/LICENSE.txt
jplephem-2.21.dist-info/METADATA
jplephem-2.21.dist-info/WHEEL
jplephem-2.21.dist-info/top_level.txt
jplephem-2.21.dist-info/RECORD
